examples/__init__.py
examples/storage.py
tableschema_spss/VERSION
tableschema_spss/__init__.py
tableschema_spss/mapper.py
tableschema_spss/storage.py
tableschema_spss-1.0.14.dist-info/LICENSE.md
tableschema_spss-1.0.14.dist-info/METADATA
tableschema_spss-1.0.14.dist-info/WHEEL
tableschema_spss-1.0.14.dist-info/top_level.txt
tableschema_spss-1.0.14.dist-info/RECORD
