Metadata-Version: 2.1
Name: tableschema-spss
Version: 1.0.14
Summary: UNKNOWN
Home-page: https://github.com/frictionlessdata/tableschema-spss-py
Author: Open Knowledge International
Author-email: info@okfn.org
License: MIT
Keywords: frictionless data,datapackage,tableschema,spss
Platform: UNKNOWN
Classifier: Development Status :: 4 - Beta
Classifier: Intended Audience :: Developers
Classifier: Intended Audience :: Science/Research
Classifier: License :: OSI Approved :: MIT License
Classifier: Operating System :: OS Independent
Classifier: Programming Language :: Python :: 2
Classifier: Programming Language :: Python :: 2.7
Classifier: Programming Language :: Python :: 3
Classifier: Programming Language :: Python :: 3.4
Classifier: Programming Language :: Python :: 3.5
Classifier: Programming Language :: Python :: 3.6
Classifier: Topic :: Scientific/Engineering :: Information Analysis
Classifier: Topic :: Software Development :: Libraries :: Python Modules
Requires-Dist: six (>=1.9)
Requires-Dist: tableschema (>=1.0)
Requires-Dist: savReaderWriter (>=3.0)
Provides-Extra: develop
Requires-Dist: mock ; extra == 'develop'
Requires-Dist: pylama ; extra == 'develop'
Requires-Dist: pytest ; extra == 'develop'
Requires-Dist: pytest-cov ; extra == 'develop'
Requires-Dist: tox ; extra == 'develop'
